{
  "pipeline_id": "PIPE-D747A501",
  "name": "Lifecycle Test",
  "opportunities": [
    {
      "opportunity_id": "OPP-AC76EB9A",
      "client_name": "Acme Corp",
      "client_email": "contact@acme.com",
      "service_title": "Website Redesign & Optimization",
      "stage": "won",
      "score": 0.4135714285714286,
      "proposal_id": null,
      "created_at": "2026-05-13T19:15:38.605549",
      "updated_at": "2026-05-13T19:15:38.605569",
      "notes": "",
      "metadata": {
        "sop_version": 1,
        "client_industry": "Technology",
        "client_budget_range": "$5000-$15000"
      }
    }
  ],
  "created_at": "2026-05-13T19:15:38.606198",
  "updated_at": "2026-05-13T19:15:38.640543"
}